dyc_package/main.py
dyc_package/person.py
dyc_package/test.py
dyc_package-1.0.3.dist-info/METADATA
dyc_package-1.0.3.dist-info/WHEEL
dyc_package-1.0.3.dist-info/top_level.txt
dyc_package-1.0.3.dist-info/RECORD
