Metadata-Version: 2.1
Name: dyc-package
Version: 1.0.3
Summary: Description of your package
Author: dyc
Author-email: your@email.com
